DiscordHelper/DiscordHelper.py
DiscordHelper/__init__.py
DiscordHelper-0.2.dist-info/METADATA
DiscordHelper-0.2.dist-info/WHEEL
DiscordHelper-0.2.dist-info/top_level.txt
DiscordHelper-0.2.dist-info/RECORD
