Metadata-Version: 2.1
Name: DiscordHelper
Version: 0.2
Summary: Discord Love
Home-page: UNKNOWN
Author: admin_01S
Author-email: discord-api@naver.com
License: MIT
Platform: UNKNOWN
Classifier: Programming Language :: Python :: 3.6
Classifier: Programming Language :: Python :: 3.7
Classifier: Programming Language :: Python :: 3.8
